lavague/gradio/__init__.py
lavague/gradio/base.py
lavague_gradio-0.2.7.dist-info/METADATA
lavague_gradio-0.2.7.dist-info/WHEEL
lavague_gradio-0.2.7.dist-info/RECORD
